fileio/__init__.py
fileio/version.py
fileio/cli/__init__.py
fileio/cli/functions.py
fileio/io/__init__.py
fileio/io/converters/__init__.py
fileio/io/converters/base.py
fileio/io/converters/static.py
fileio/io/generic/__init__.py
fileio/io/generic/_json.py
fileio/io/generic/base.py
fileio/io/generic/base64.py
fileio/io/generic/base64gzip.py
fileio/io/generic/csv.py
fileio/io/generic/generator.py
fileio/io/generic/jsonlines.py
fileio/io/generic/msgpack.py
fileio/io/generic/pickle.py
fileio/io/generic/text.py
fileio/io/generic/tsv.py
fileio/io/generic/yaml.py
fileio/lib/__init__.py
fileio/lib/apis.py
fileio/lib/base.py
fileio/lib/core.py
fileio/lib/exceptions.py
fileio/lib/flavours.py
fileio/lib/pathz.py
fileio/lib/types.py
fileio/lib/aiopath/__init__.py
fileio/lib/aiopath/handle.py
fileio/lib/aiopath/readme.md
fileio/lib/aiopath/scandir.py
fileio/lib/aiopath/selectors.py
fileio/lib/aiopath/wrap.py
fileio/lib/posix/__init__.py
fileio/lib/posix/base.py
fileio/lib/posix/cloud.py
fileio/lib/posix/filesys.py
fileio/lib/posix/meta.py
fileio/lib/posix/static.py
fileio/providers/__init__.py
fileio/providers/azure.py
fileio/providers/gcs.py
fileio/providers/minio.py
fileio/providers/r2.py
fileio/providers/s3.py
fileio/providers/s3c.py
fileio/providers/tfio.py
fileio/providers/wasabi.py
fileio/providers/filesys/__init__.py
fileio/providers/filesys/wasabi_s3.py
fileio/providers/filesys/aws_s3/__init__.py
fileio/providers/filesys/aws_s3/base.py
fileio/providers/filesys/aws_s3/filesys.py
fileio/providers/filesys/aws_s3/utils.py
fileio/providers/filesys/cloudflare_r2/__init__.py
fileio/providers/filesys/cloudflare_r2/base.py
fileio/providers/filesys/cloudflare_r2/constants.py
fileio/providers/filesys/cloudflare_r2/filesys.py
fileio/providers/filesys/cloudflare_r2/utils.py
fileio/types/__init__.py
fileio/types/classprops.py
fileio/types/common.py
fileio/types/etc.py
fileio/types/options.py
fileio/utils/__init__.py
fileio/utils/configs.py
fileio/utils/helpers.py
file_io-0.5.0.dist-info/LICENSE
file_io-0.5.0.dist-info/METADATA
file_io-0.5.0.dist-info/WHEEL
file_io-0.5.0.dist-info/entry_points.txt
file_io-0.5.0.dist-info/top_level.txt
file_io-0.5.0.dist-info/RECORD
