Metadata-Version: 2.1
Name: file-io
Version: 0.5.0
Summary: Deterministic File Lib to make working with Files across Object Storage easier
Home-page: https://github.com/trisongz/file-io
Author: Tri Songz
Author-email: ts@growthengineai.com
License: MIT Style
Classifier: Intended Audience :: Developers
Classifier: License :: OSI Approved :: MIT License
Classifier: Programming Language :: Python :: 3.9
Classifier: Topic :: Software Development :: Libraries
License-File: LICENSE
Requires-Dist: anyio
Requires-Dist: aiofile
Requires-Dist: fsspec
Requires-Dist: loguru
Requires-Dist: pydantic
Requires-Dist: dill
Requires-Dist: frozendict
Requires-Dist: aiohttpx
Requires-Dist: typer
Provides-Extra: cloud
Requires-Dist: gcsfs ; extra == 'cloud'
Requires-Dist: s3fs ; extra == 'cloud'
Provides-Extra: gcs
Requires-Dist: gcsfs ; extra == 'gcs'
Provides-Extra: s3
Requires-Dist: s3fs ; extra == 's3'
